lb_sdk/__init__.py
lb_sdk/localbitcoins_sdk.py
localbitcoins_sdk/__init__.py
localbitcoins_sdk/localbitcoins_sdk.py
localbitcoins_sdk-0.0.4.dist-info/LICENSE
localbitcoins_sdk-0.0.4.dist-info/METADATA
localbitcoins_sdk-0.0.4.dist-info/WHEEL
localbitcoins_sdk-0.0.4.dist-info/top_level.txt
localbitcoins_sdk-0.0.4.dist-info/RECORD
