Metadata-Version: 2.1
Name: localbitcoins-sdk
Version: 0.0.4
Summary: A simple sdk for working with LocalBitcoins API
Home-page: https://github.com/exelay/localbitcoins-sdk
Author: Aleksei Kirpa
Author-email: exelay.rapik@gmail.com
License: UNKNOWN
Platform: UNKNOWN
Classifier: Programming Language :: Python :: 3.8
Classifier: License :: OSI Approved :: GNU General Public License v3 (GPLv3)
Requires-Dist: requests (>=2)
